CHANGES.txt
CREDITS.txt
README.txt
bootstrap.py
buildout.cfg
setup.py
src/megrok/__init__.py
src/megrok.tinymce.egg-info/PKG-INFO
src/megrok.tinymce.egg-info/SOURCES.txt
src/megrok.tinymce.egg-info/dependency_links.txt
src/megrok.tinymce.egg-info/entry_points.txt
src/megrok.tinymce.egg-info/namespace_packages.txt
src/megrok.tinymce.egg-info/not-zip-safe
src/megrok.tinymce.egg-info/requires.txt
src/megrok.tinymce.egg-info/top_level.txt
src/megrok/tinymce/__init__.py
src/megrok/tinymce/configure.zcml
src/megrok/tinymce/resource.py
src/megrok/tinymce/tiny_mce/license.txt
src/megrok/tinymce/tiny_mce/tiny_mce.js
src/megrok/tinymce/tiny_mce/tiny_mce_popup.js
src/megrok/tinymce/tiny_mce/tiny_mce_src.js
src/megrok/tinymce/tiny_mce/langs/en.js
src/megrok/tinymce/tiny_mce/plugins/advhr/editor_plugin.js
src/megrok/tinymce/tiny_mce/plugins/advhr/editor_plugin_src.js
src/megrok/tinymce/tiny_mce/plugins/advhr/rule.htm
src/megrok/tinymce/tiny_mce/plugins/advhr/css/advhr.css
src/megrok/tinymce/tiny_mce/plugins/advhr/js/rule.js
src/megrok/tinymce/tiny_mce/plugins/advhr/langs/en_dlg.js
src/megrok/tinymce/tiny_mce/plugins/advimage/editor_plugin.js
src/megrok/tinymce/tiny_mce/plugins/advimage/editor_plugin_src.js
src/megrok/tinymce/tiny_mce/plugins/advimage/image.htm
src/megrok/tinymce/tiny_mce/plugins/advimage/css/advimage.css
src/megrok/tinymce/tiny_mce/plugins/advimage/img/sample.gif
src/megrok/tinymce/tiny_mce/plugins/advimage/js/image.js
src/megrok/tinymce/tiny_mce/plugins/advimage/langs/en_dlg.js
src/megrok/tinymce/tiny_mce/plugins/advlink/editor_plugin.js
src/megrok/tinymce/tiny_mce/plugins/advlink/editor_plugin_src.js
src/megrok/tinymce/tiny_mce/plugins/advlink/link.htm
src/megrok/tinymce/tiny_mce/plugins/advlink/css/advlink.css
src/megrok/tinymce/tiny_mce/plugins/advlink/js/advlink.js
src/megrok/tinymce/tiny_mce/plugins/advlink/langs/en_dlg.js
src/megrok/tinymce/tiny_mce/plugins/autosave/editor_plugin.js
src/megrok/tinymce/tiny_mce/plugins/autosave/editor_plugin_src.js
src/megrok/tinymce/tiny_mce/plugins/bbcode/editor_plugin.js
src/megrok/tinymce/tiny_mce/plugins/bbcode/editor_plugin_src.js
src/megrok/tinymce/tiny_mce/plugins/compat2x/editor_plugin.js
src/megrok/tinymce/tiny_mce/plugins/compat2x/editor_plugin_src.js
src/megrok/tinymce/tiny_mce/plugins/contextmenu/editor_plugin.js
