Metadata-Version: 1.0
Name: megrok.tinymce
Version: 3.1.0.1.1
Summary: TinyMCE javascript editor packaged as a Grok resource library.
Home-page: UNKNOWN
Author: Grok Team, 
Author-email: grok-dev@zope.org
License: LGPL
Platform: UNKNOWN
Classifier: Programming Language :: Python
Classifier: Programming Language :: JavaScript
Classifier: Framework :: Zope3
Classifier: Topic :: Software Development :: Libraries :: Python Modules
